Metadata-Version: 2.1
Name: elucidatacmapPy
Version: 3.3.4
Summary: Assorted tools for interacting with .gct, .gctx files and other Connectivity Map (Broad Institute) data/tools
Home-page: https://github.com/cmap/cmapPy
Maintainer: Oana Enache
Maintainer-email: oana@broadinstitute.org
License: BSD 3-clause
Keywords: gct gctx file-manipulation Connectivity Map CMap Broad Institute
Classifier: Development Status :: 5 - Production/Stable
Classifier: Intended Audience :: Science/Research
Classifier: Topic :: Scientific/Engineering :: Bio-Informatics
Classifier: License :: OSI Approved :: BSD License
Classifier: Programming Language :: Python :: 2
Classifier: Programming Language :: Python :: 2.7
License-File: LICENSE.txt
Requires-Dist: numpy (>=1.11.2)
Requires-Dist: pandas (>=0.18)
Requires-Dist: h5py (>=2.6.0)
Requires-Dist: requests (>=2.13.0)
Requires-Dist: six
